{
  "$schema": "https://design-tokens.github.io/community-group/format/dtcg.schema.json",
  "$metadata": {
    "id": "lkany.theme",
    "version": "1.4.0",
    "updated": "2025-05-13T00:00:00.000Z",
    "description": "Design tokens powering the LKANY interface theme.",
    "source": "src/theme.js"
  },
  "color": {
    "$description": "Color primitives including ramps and semantic themes.",
    "ramps": {
      "primary": {
        "50": { "$type": "color", "$value": "#FFF3F5" },
        "100": { "$type": "color", "$value": "#FFE0E5" },
        "200": { "$type": "color", "$value": "#FFBAC4" },
        "300": { "$type": "color", "$value": "#FF8899" },
        "400": { "$type": "color", "$value": "#F85A73" },
        "500": { "$type": "color", "$value": "#E83856" },
        "600": { "$type": "color", "$value": "#C8183A" },
        "700": { "$type": "color", "$value": "#9A112C" },
        "800": { "$type": "color", "$value": "#6C0A1D" },
        "900": { "$type": "color", "$value": "#39040F" },
        "$description": "Radiant ruby reds used for primary actions and key highlights."
      },
      "accent": {
        "50": { "$type": "color", "$value": "#FFF6F1" },
        "100": { "$type": "color", "$value": "#FFE7D9" },
        "200": { "$type": "color", "$value": "#FFCEB3" },
        "300": { "$type": "color", "$value": "#FFAF86" },
        "400": { "$type": "color", "$value": "#FF905C" },
        "500": { "$type": "color", "$value": "#F26F3E" },
        "600": { "$type": "color", "$value": "#CC5126" },
        "700": { "$type": "color", "$value": "#A03A1B" },
        "800": { "$type": "color", "$value": "#702611" },
        "900": { "$type": "color", "$value": "#3A1409" },
        "$description": "Sunlit apricot accents for warmth, focus states, and data viz."
      },
      "neutral": {
        "50": { "$type": "color", "$value": "#FFF7F7" },
        "100": { "$type": "color", "$value": "#FBE9E9" },
        "200": { "$type": "color", "$value": "#F3D4D5" },
        "300": { "$type": "color", "$value": "#E4B4B7" },
        "400": { "$type": "color", "$value": "#C89094" },
        "500": { "$type": "color", "$value": "#A76F74" },
        "600": { "$type": "color", "$value": "#825359" },
        "700": { "$type": "color", "$value": "#5D3A3F" },
        "800": { "$type": "color", "$value": "#3A2327" },
        "900": { "$type": "color", "$value": "#1F1114" },
        "$description": "Blushed neutrals tuned for typography, backgrounds, and borders."
      },
      "success": {
        "50": { "$type": "color", "$value": "#ECFDF5" },
        "100": { "$type": "color", "$value": "#D1FAE5" },
        "200": { "$type": "color", "$value": "#A7F3D0" },
        "300": { "$type": "color", "$value": "#6EE7B7" },
        "400": { "$type": "color", "$value": "#34D399" },
        "500": { "$type": "color", "$value": "#10B981" },
        "600": { "$type": "color", "$value": "#059669" }
      },
      "info": {
        "50": { "$type": "color", "$value": "#F0F9FF" },
        "100": { "$type": "color", "$value": "#E0F2FE" },
        "200": { "$type": "color", "$value": "#BAE6FD" },
        "300": { "$type": "color", "$value": "#7DD3FC" },
        "400": { "$type": "color", "$value": "#38BDF8" },
        "500": { "$type": "color", "$value": "#0EA5E9" },
        "600": { "$type": "color", "$value": "#0284C7" }
      },
      "warning": {
        "50": { "$type": "color", "$value": "#FFFBEB" },
        "100": { "$type": "color", "$value": "#FEF3C7" },
        "200": { "$type": "color", "$value": "#FDE68A" },
        "300": { "$type": "color", "$value": "#FCD34D" },
        "400": { "$type": "color", "$value": "#FBBF24" },
        "500": { "$type": "color", "$value": "#F59E0B" },
        "600": { "$type": "color", "$value": "#D97706" }
      },
      "danger": {
        "50": { "$type": "color", "$value": "#FFF2F3" },
        "100": { "$type": "color", "$value": "#FFE1E3" },
        "200": { "$type": "color", "$value": "#FFC1C6" },
        "300": { "$type": "color", "$value": "#FF969F" },
        "400": { "$type": "color", "$value": "#F56A78" },
        "500": { "$type": "color", "$value": "#E23D4E" },
        "600": { "$type": "color", "$value": "#BB1F32" }
      }
    },
    "themes": {
      "light": {
        "name": "Light+",
        "bg": "#FFF7F8",
        "surface": "#FFE8EC",
        "surfaceAlt": "#FFD4DB",
        "surfaceMuted": "#F9BEC7",
        "text": "#410610",
        "textMuted": "#9A112C",
        "textMutedStrong": "#6C0A1D",
        "textInverse": "#FFF9FA",
        "buttonText": "#2C040B",
        "primary": "#C8183A",
        "primaryContrast": "#FFF7F8",
        "primarySoft": "rgba(200, 24, 58, 0.16)",
        "secondary": "#F26F3E",
        "accent": "#F26F3E",
        "success": "#10B981",
        "info": "#0EA5E9",
        "warning": "#F59E0B",
        "danger": "#BB1F32",
        "border": "rgba(154, 17, 44, 0.28)",
        "borderMuted": "rgba(154, 17, 44, 0.18)",
        "borderStrong": "rgba(76, 8, 21, 0.42)",
        "muted": "rgba(200, 24, 58, 0.1)",
        "ring": "rgba(232, 56, 86, 0.42)",
        "overlay": "rgba(62, 6, 20, 0.24)",
        "scrim": "rgba(45, 5, 16, 0.2)",
        "backgroundImage": "radial-gradient(1240px 620px at 12% -14%, rgba(232, 56, 86, 0.16), transparent 72%), radial-gradient(920px 520px at 88% -6%, rgba(200, 24, 58, 0.12), transparent 78%)",
        "components": {
          "button": {
            "primary": {
              "bg": "#C8183A",
              "fg": "#FFF7F8",
              "border": "transparent",
              "hoverBg": "#E83856",
              "hoverFg": "#FFF7F8",
              "hoverBorder": "transparent",
              "shadow": "0 12px 32px rgba(154, 17, 44, 0.24)",
              "hoverShadow": "0 16px 36px rgba(154, 17, 44, 0.3)",
              "spinner": "rgba(255, 244, 250, 0.78)"
            },
            "secondary": {
              "bg": "#FFD4DB",
              "fg": "#410610",
              "border": "rgba(154, 17, 44, 0.35)",
              "hoverBg": "#FFE8EC",
              "hoverFg": "#C8183A",
              "hoverBorder": "rgba(154, 17, 44, 0.55)",
              "shadow": "0 6px 18px rgba(154, 17, 44, 0.16)",
              "hoverShadow": "0 8px 22px rgba(154, 17, 44, 0.22)",
              "spinner": "rgba(62, 6, 20, 0.55)"
            },
            "subtle": {
              "bg": "rgba(200, 24, 58, 0.16)",
              "fg": "#C8183A",
              "border": "rgba(200, 24, 58, 0.38)",
              "hoverBg": "rgba(154, 17, 44, 0.24)",
              "hoverFg": "#C8183A",
              "hoverBorder": "rgba(200, 24, 58, 0.58)",
              "shadow": "none",
              "hoverShadow": "none",
              "spinner": "rgba(154, 17, 44, 0.72)"
            },
            "ghost": {
              "bg": "transparent",
              "fg": "#410610",
              "border": "transparent",
              "hoverBg": "rgba(154, 17, 44, 0.1)",
              "hoverFg": "#C8183A",
              "hoverBorder": "transparent",
              "shadow": "none",
              "hoverShadow": "none",
              "spinner": "rgba(62, 6, 20, 0.5)"
            },
            "destructive": {
              "bg": "#BB1F32",
              "fg": "#2C040B",
              "border": "transparent",
              "hoverBg": "#E23D4E",
              "hoverFg": "#2C040B",
              "hoverBorder": "transparent",
              "shadow": "0 12px 30px rgba(187, 31, 50, 0.24)",
              "hoverShadow": "0 16px 34px rgba(187, 31, 50, 0.32)",
              "spinner": "rgba(62, 6, 20, 0.6)"
            },
            "tone": {
              "neutral": {
                "bg": "#F9BEC7",
                "fg": "#410610",
                "border": "rgba(154, 17, 44, 0.32)",
                "hoverBg": "#FFE8EC",
                "hoverFg": "#410610",
                "hoverBorder": "rgba(154, 17, 44, 0.45)",
                "shadow": "none",
                "hoverShadow": "none",
                "spinner": "rgba(154, 17, 44, 0.55)"
              },
              "accent": {
                "bg": "rgba(242, 111, 62, 0.16)",
                "fg": "#F26F3E",
                "border": "rgba(242, 111, 62, 0.42)",
                "hoverBg": "rgba(242, 111, 62, 0.22)",
                "hoverFg": "#F26F3E",
                "hoverBorder": "rgba(242, 111, 62, 0.55)",
                "shadow": "none",
                "hoverShadow": "none",
                "spinner": "rgba(204, 81, 38, 0.82)"
              },
              "info": {
                "bg": "rgba(14, 165, 233, 0.16)",
                "fg": "#0EA5E9",
                "border": "rgba(14, 165, 233, 0.42)",
                "hoverBg": "rgba(14, 165, 233, 0.23)",
                "hoverFg": "#0EA5E9",
                "hoverBorder": "rgba(14, 165, 233, 0.55)",
                "shadow": "none",
                "hoverShadow": "none",
                "spinner": "rgba(14, 165, 233, 0.82)"
              },
              "success": {
                "bg": "rgba(16, 185, 129, 0.16)",
                "fg": "#10B981",
                "border": "rgba(16, 185, 129, 0.42)",
                "hoverBg": "rgba(16, 185, 129, 0.22)",
                "hoverFg": "#10B981",
                "hoverBorder": "rgba(16, 185, 129, 0.55)",
                "shadow": "none",
                "hoverShadow": "none",
                "spinner": "rgba(16, 185, 129, 0.8)"
              },
              "warning": {
                "bg": "rgba(245, 158, 11, 0.22)",
                "fg": "#F59E0B",
                "border": "rgba(245, 158, 11, 0.45)",
                "hoverBg": "rgba(245, 158, 11, 0.28)",
                "hoverFg": "#F59E0B",
                "hoverBorder": "rgba(245, 158, 11, 0.58)",
                "shadow": "none",
                "hoverShadow": "none",
                "spinner": "rgba(245, 158, 11, 0.8)"
              },
              "danger": {
                "bg": "rgba(226, 61, 78, 0.22)",
                "fg": "#BB1F32",
                "border": "rgba(226, 61, 78, 0.48)",
                "hoverBg": "rgba(226, 61, 78, 0.28)",
                "hoverFg": "#BB1F32",
                "hoverBorder": "rgba(226, 61, 78, 0.6)",
                "shadow": "none",
                "hoverShadow": "none",
                "spinner": "rgba(226, 61, 78, 0.82)"
              }
            }
          },
          "badge": {
            "neutral": {
              "soft": {
                "bg": "rgba(154, 17, 44, 0.16)",
                "border": "rgba(154, 17, 44, 0.32)",
                "fg": "#9A112C"
              },
              "solid": {
                "bg": "#9A112C",
                "border": "transparent",
                "fg": "#FFF9FA"
              },
              "outline": {
                "bg": "transparent",
                "border": "rgba(154, 17, 44, 0.48)",
                "fg": "#9A112C"
              }
            },
            "primary": {
              "soft": {
                "bg": "rgba(200, 24, 58, 0.12)",
                "border": "rgba(200, 24, 58, 0.32)",
                "fg": "#C8183A"
              },
              "solid": {
                "bg": "#C8183A",
                "border": "transparent",
                "fg": "#FFF7F8"
              },
              "outline": {
                "bg": "transparent",
                "border": "rgba(200, 24, 58, 0.48)",
                "fg": "#C8183A"
              }
            },
            "accent": {
              "soft": {
                "bg": "rgba(242, 111, 62, 0.14)",
                "border": "rgba(242, 111, 62, 0.34)",
                "fg": "#F26F3E"
              },
              "solid": {
                "bg": "#F26F3E",
                "border": "transparent",
                "fg": "#FFF7F8"
              },
              "outline": {
                "bg": "transparent",
                "border": "rgba(242, 111, 62, 0.5)",
                "fg": "#F26F3E"
              }
            },
            "success": {
              "soft": {
                "bg": "rgba(16, 185, 129, 0.16)",
                "border": "rgba(16, 185, 129, 0.32)",
                "fg": "#10B981"
              },
              "solid": {
                "bg": "#10B981",
                "border": "transparent",
                "fg": "#FFF9FA"
              },
              "outline": {
                "bg": "transparent",
                "border": "rgba(16, 185, 129, 0.45)",
                "fg": "#10B981"
              }
            },
            "info": {
              "soft": {
                "bg": "rgba(14, 165, 233, 0.18)",
                "border": "rgba(14, 165, 233, 0.32)",
                "fg": "#0EA5E9"
              },
              "solid": {
                "bg": "#0EA5E9",
                "border": "transparent",
                "fg": "#FFF9FA"
              },
              "outline": {
                "bg": "transparent",
                "border": "rgba(14, 165, 233, 0.45)",
                "fg": "#0EA5E9"
              }
            },
            "warning": {
              "soft": {
                "bg": "rgba(245, 158, 11, 0.2)",
                "border": "rgba(245, 158, 11, 0.4)",
                "fg": "#F59E0B"
              },
              "solid": {
                "bg": "#F59E0B",
                "border": "transparent",
                "fg": "#FFF9FA"
              },
              "outline": {
                "bg": "transparent",
                "border": "rgba(245, 158, 11, 0.55)",
                "fg": "#F59E0B"
              }
            },
            "danger": {
              "soft": {
                "bg": "rgba(226, 61, 78, 0.22)",
                "border": "rgba(226, 61, 78, 0.48)",
                "fg": "#BB1F32"
              },
              "solid": {
                "bg": "#BB1F32",
                "border": "transparent",
                "fg": "#FFF9FA"
              },
              "outline": {
                "bg": "transparent",
                "border": "rgba(226, 61, 78, 0.6)",
                "fg": "#BB1F32"
              }
            }
          }
        }
      },
      "dark": {
        "name": "Dark+",
        "bg": "#140208",
        "surface": "#1C040D",
        "surfaceAlt": "#260512",
        "surfaceMuted": "#33081A",
        "text": "#FFE3E7",
        "textMuted": "#FF9FB2",
        "textMutedStrong": "#FFC1CC",
        "textInverse": "#1B0308",
        "buttonText": "#180309",
        "primary": "#F85A73",
        "primaryContrast": "#1B0308",
        "primarySoft": "rgba(232, 56, 86, 0.22)",
        "secondary": "#FF905C",
        "accent": "#FF905C",
        "success": "#6EE7B7",
        "info": "#7DD3FC",
        "warning": "#FBBF24",
        "danger": "#F56A78",
        "border": "rgba(232, 56, 86, 0.28)",
        "borderMuted": "rgba(232, 56, 86, 0.18)",
        "borderStrong": "rgba(232, 56, 86, 0.38)",
        "muted": "rgba(232, 56, 86, 0.16)",
        "ring": "rgba(232, 56, 86, 0.52)",
        "overlay": "rgba(12, 2, 5, 0.72)",
        "scrim": "rgba(12, 2, 5, 0.54)",
        "backgroundImage": "radial-gradient(1320px 600px at 12% -16%, rgba(232, 56, 86, 0.3), transparent 72%), radial-gradient(1000px 600px at 84% -8%, rgba(200, 24, 58, 0.22), transparent 76%), linear-gradient(180deg, #140208 0%, #1F0410 46%, #31081B 100%)",
        "components": {
          "button": {
            "primary": {
              "bg": "#F85A73",
              "fg": "#1B0308",
              "border": "transparent",
              "hoverBg": "#FF8899",
              "hoverFg": "#1B0308",
              "hoverBorder": "transparent",
              "shadow": "0 12px 32px rgba(154, 17, 44, 0.32)",
              "hoverShadow": "0 16px 36px rgba(154, 17, 44, 0.38)",
              "spinner": "rgba(255, 237, 245, 0.7)"
            },
            "secondary": {
              "bg": "#260512",
              "fg": "#FFE3E7",
              "border": "rgba(232, 56, 86, 0.28)",
              "hoverBg": "#1C040D",
              "hoverFg": "#F85A73",
              "hoverBorder": "rgba(232, 56, 86, 0.45)",
              "shadow": "0 8px 24px rgba(12, 1, 5, 0.48)",
              "hoverShadow": "0 10px 28px rgba(12, 1, 5, 0.55)",
              "spinner": "rgba(232, 56, 86, 0.6)"
            },
            "subtle": {
              "bg": "rgba(232, 56, 86, 0.22)",
              "fg": "#F85A73",
              "border": "rgba(232, 56, 86, 0.38)",
              "hoverBg": "rgba(154, 17, 44, 0.22)",
              "hoverFg": "#F85A73",
              "hoverBorder": "rgba(232, 56, 86, 0.58)",
              "shadow": "none",
              "hoverShadow": "none",
              "spinner": "rgba(232, 56, 86, 0.75)"
            },
            "ghost": {
              "bg": "transparent",
              "fg": "#FFE3E7",
              "border": "transparent",
              "hoverBg": "rgba(232, 56, 86, 0.12)",
              "hoverFg": "#F85A73",
              "hoverBorder": "transparent",
              "shadow": "none",
              "hoverShadow": "none",
              "spinner": "rgba(232, 56, 86, 0.65)"
            },
            "destructive": {
              "bg": "#F56A78",
              "fg": "#180309",
              "border": "transparent",
              "hoverBg": "#E23D4E",
              "hoverFg": "#180309",
              "hoverBorder": "transparent",
              "shadow": "0 12px 30px rgba(187, 31, 50, 0.32)",
              "hoverShadow": "0 16px 34px rgba(187, 31, 50, 0.4)",
              "spinner": "rgba(232, 56, 86, 0.65)"
            },
            "tone": {
              "neutral": {
                "bg": "#260512",
                "fg": "#FFE3E7",
                "border": "rgba(232, 56, 86, 0.32)",
                "hoverBg": "#1C040D",
                "hoverFg": "#FFE3E7",
                "hoverBorder": "rgba(232, 56, 86, 0.45)",
                "shadow": "none",
                "hoverShadow": "none",
                "spinner": "rgba(232, 56, 86, 0.6)"
              },
              "accent": {
                "bg": "rgba(255, 144, 92, 0.18)",
                "fg": "#FF905C",
                "border": "rgba(255, 144, 92, 0.45)",
                "hoverBg": "rgba(255, 144, 92, 0.24)",
                "hoverFg": "#FF905C",
                "hoverBorder": "rgba(255, 144, 92, 0.58)",
                "shadow": "none",
                "hoverShadow": "none",
                "spinner": "rgba(255, 144, 92, 0.8)"
              },
              "info": {
                "bg": "rgba(56, 189, 248, 0.2)",
                "fg": "#7DD3FC",
                "border": "rgba(56, 189, 248, 0.48)",
                "hoverBg": "rgba(56, 189, 248, 0.26)",
                "hoverFg": "#7DD3FC",
                "hoverBorder": "rgba(56, 189, 248, 0.6)",
                "shadow": "none",
                "hoverShadow": "none",
                "spinner": "rgba(56, 189, 248, 0.82)"
              },
              "success": {
                "bg": "rgba(110, 231, 183, 0.2)",
                "fg": "#6EE7B7",
                "border": "rgba(110, 231, 183, 0.5)",
                "hoverBg": "rgba(110, 231, 183, 0.28)",
                "hoverFg": "#6EE7B7",
                "hoverBorder": "rgba(110, 231, 183, 0.6)",
                "shadow": "none",
                "hoverShadow": "none",
                "spinner": "rgba(110, 231, 183, 0.82)"
              },
              "warning": {
                "bg": "rgba(251, 191, 36, 0.24)",
                "fg": "#FBBF24",
                "border": "rgba(251, 191, 36, 0.55)",
                "hoverBg": "rgba(251, 191, 36, 0.32)",
                "hoverFg": "#FBBF24",
                "hoverBorder": "rgba(251, 191, 36, 0.65)",
                "shadow": "none",
                "hoverShadow": "none",
                "spinner": "rgba(251, 191, 36, 0.8)"
              },
              "danger": {
                "bg": "rgba(226, 61, 78, 0.24)",
                "fg": "#F56A78",
                "border": "rgba(226, 61, 78, 0.52)",
                "hoverBg": "rgba(226, 61, 78, 0.32)",
                "hoverFg": "#F56A78",
                "hoverBorder": "rgba(226, 61, 78, 0.65)",
                "shadow": "none",
                "hoverShadow": "none",
                "spinner": "rgba(226, 61, 78, 0.82)"
              }
            }
          },
          "badge": {
            "neutral": {
              "soft": {
                "bg": "rgba(232, 56, 86, 0.16)",
                "border": "rgba(232, 56, 86, 0.32)",
                "fg": "#FF9FB2"
              },
              "solid": {
                "bg": "#FF9FB2",
                "border": "transparent",
                "fg": "#1B0308"
              },
              "outline": {
                "bg": "transparent",
                "border": "rgba(232, 56, 86, 0.48)",
                "fg": "#FF9FB2"
              }
            },
            "primary": {
              "soft": {
                "bg": "rgba(248, 90, 115, 0.12)",
                "border": "rgba(248, 90, 115, 0.32)",
                "fg": "#F85A73"
              },
              "solid": {
                "bg": "#F85A73",
                "border": "transparent",
                "fg": "#1B0308"
              },
              "outline": {
                "bg": "transparent",
                "border": "rgba(248, 90, 115, 0.48)",
                "fg": "#F85A73"
              }
            },
            "accent": {
              "soft": {
                "bg": "rgba(255, 144, 92, 0.16)",
                "border": "rgba(255, 144, 92, 0.34)",
                "fg": "#FF905C"
              },
              "solid": {
                "bg": "#FF905C",
                "border": "transparent",
                "fg": "#1B0308"
              },
              "outline": {
                "bg": "transparent",
                "border": "rgba(255, 144, 92, 0.5)",
                "fg": "#FF905C"
              }
            },
            "success": {
              "soft": {
                "bg": "rgba(110, 231, 183, 0.2)",
                "border": "rgba(110, 231, 183, 0.42)",
                "fg": "#6EE7B7"
              },
              "solid": {
                "bg": "#6EE7B7",
                "border": "transparent",
                "fg": "#1B0308"
              },
              "outline": {
                "bg": "transparent",
                "border": "rgba(110, 231, 183, 0.55)",
                "fg": "#6EE7B7"
              }
            },
            "info": {
              "soft": {
                "bg": "rgba(125, 211, 252, 0.2)",
                "border": "rgba(125, 211, 252, 0.42)",
                "fg": "#7DD3FC"
              },
              "solid": {
                "bg": "#7DD3FC",
                "border": "transparent",
                "fg": "#1B0308"
              },
              "outline": {
                "bg": "transparent",
                "border": "rgba(125, 211, 252, 0.55)",
                "fg": "#7DD3FC"
              }
            },
            "warning": {
              "soft": {
                "bg": "rgba(251, 191, 36, 0.24)",
                "border": "rgba(251, 191, 36, 0.45)",
                "fg": "#FBBF24"
              },
              "solid": {
                "bg": "#FBBF24",
                "border": "transparent",
                "fg": "#1B0308"
              },
              "outline": {
                "bg": "transparent",
                "border": "rgba(251, 191, 36, 0.6)",
                "fg": "#FBBF24"
              }
            },
            "danger": {
              "soft": {
                "bg": "rgba(226, 61, 78, 0.24)",
                "border": "rgba(226, 61, 78, 0.48)",
                "fg": "#F56A78"
              },
              "solid": {
                "bg": "#F56A78",
                "border": "transparent",
                "fg": "#1B0308"
              },
              "outline": {
                "bg": "transparent",
                "border": "rgba(226, 61, 78, 0.6)",
                "fg": "#F56A78"
              }
            }
          }
        }
      }
    }
  },
  "typography": {
    "$description": "Fluid typography scale and type system foundations.",
    "families": {
      "sans": "'Tajawal', 'Plus Jakarta Sans', 'Inter', 'Segoe UI', system-ui, sans-serif",
      "display": "'Space Grotesk', 'Tajawal', 'Plus Jakarta Sans', 'Inter', 'Segoe UI', system-ui, sans-serif",
      "mono": "'JetBrains Mono', 'SFMono-Regular', Consolas, monospace"
    },
    "weights": {
      "regular": 400,
      "medium": 500,
      "semibold": 600,
      "bold": 700,
      "extrabold": 800
    },
    "scale": {
      "50": {
        "fontSize": "clamp(0.6875rem, 0.6725rem + 0.1vw, 0.725rem)",
        "lineHeight": "clamp(1rem, 0.97rem + 0.08vw, 1.05rem)",
        "letterSpacing": "0.04em"
      },
      "75": {
        "fontSize": "clamp(0.75rem, 0.73rem + 0.12vw, 0.82rem)",
        "lineHeight": "clamp(1.05rem, 1rem + 0.1vw, 1.12rem)",
        "letterSpacing": "0.03em"
      },
      "100": {
        "fontSize": "clamp(0.8125rem, 0.78rem + 0.15vw, 0.9rem)",
        "lineHeight": "clamp(1.1rem, 1.04rem + 0.12vw, 1.22rem)",
        "letterSpacing": "0.02em"
      },
      "200": {
        "fontSize": "clamp(0.875rem, 0.82rem + 0.2vw, 1rem)",
        "lineHeight": "clamp(1.2rem, 1.12rem + 0.16vw, 1.35rem)",
        "letterSpacing": "0.015em"
      },
      "300": {
        "fontSize": "clamp(0.9375rem, 0.87rem + 0.24vw, 1.06rem)",
        "lineHeight": "clamp(1.35rem, 1.25rem + 0.2vw, 1.55rem)",
        "letterSpacing": "0.01em"
      },
      "400": {
        "fontSize": "clamp(1rem, 0.94rem + 0.3vw, 1.125rem)",
        "lineHeight": "clamp(1.45rem, 1.32rem + 0.36vw, 1.68rem)",
        "letterSpacing": "0em"
      },
      "500": {
        "fontSize": "clamp(1.125rem, 1.03rem + 0.38vw, 1.3rem)",
        "lineHeight": "clamp(1.55rem, 1.42rem + 0.4vw, 1.85rem)",
        "letterSpacing": "-0.005em"
      },
      "600": {
        "fontSize": "clamp(1.25rem, 1.12rem + 0.48vw, 1.5rem)",
        "lineHeight": "clamp(1.6rem, 1.48rem + 0.45vw, 2rem)",
        "letterSpacing": "-0.01em"
      },
      "700": {
        "fontSize": "clamp(1.5rem, 1.32rem + 0.62vw, 1.85rem)",
        "lineHeight": "clamp(1.75rem, 1.58rem + 0.58vw, 2.2rem)",
        "letterSpacing": "-0.012em"
      },
      "800": {
        "fontSize": "clamp(1.875rem, 1.62rem + 0.82vw, 2.25rem)",
        "lineHeight": "clamp(2.1rem, 1.88rem + 0.75vw, 2.55rem)",
        "letterSpacing": "-0.015em"
      },
      "900": {
        "fontSize": "clamp(2.25rem, 1.96rem + 1vw, 2.65rem)",
        "lineHeight": "clamp(2.4rem, 2.1rem + 0.9vw, 2.95rem)",
        "letterSpacing": "-0.018em"
      },
      "1000": {
        "fontSize": "clamp(3rem, 2.5rem + 1.4vw, 3.5rem)",
        "lineHeight": "clamp(3.2rem, 2.7rem + 1.6vw, 3.8rem)",
        "letterSpacing": "-0.02em"
      }
    }
  },
  "spacing": {
    "$description": "Fluid spacing scale used throughout layout primitives.",
    "0": "0px",
    "1": "clamp(0.25rem, 0.22rem + 0.12vw, 0.4rem)",
    "2": "clamp(0.45rem, 0.38rem + 0.16vw, 0.65rem)",
    "3": "clamp(0.6rem, 0.5rem + 0.2vw, 0.85rem)",
    "4": "clamp(0.85rem, 0.72rem + 0.26vw, 1.2rem)",
    "5": "clamp(1.1rem, 0.92rem + 0.32vw, 1.5rem)",
    "6": "clamp(1.35rem, 1.12rem + 0.4vw, 1.85rem)",
    "7": "clamp(1.6rem, 1.28rem + 0.48vw, 2.1rem)",
    "8": "clamp(1.9rem, 1.5rem + 0.6vw, 2.4rem)",
    "9": "clamp(2.2rem, 1.7rem + 0.72vw, 2.8rem)",
    "10": "clamp(2.6rem, 2rem + 0.84vw, 3.4rem)",
    "11": "clamp(3rem, 2.3rem + 0.96vw, 3.8rem)",
    "12": "clamp(3.4rem, 2.6rem + 1.05vw, 4.2rem)",
    "13": "clamp(3.8rem, 2.9rem + 1.2vw, 4.8rem)",
    "14": "clamp(4.4rem, 3.3rem + 1.35vw, 5.6rem)",
    "15": "clamp(5rem, 3.7rem + 1.5vw, 6.6rem)"
  },
  "layout": {
    "$description": "Global layout sizing primitives.",
    "gutterInline": "clamp(0.9rem, 3.75vw, 2.5rem)",
    "gutterBlock": "clamp(1.1rem, 5.25vw, 3rem)",
    "stackGap": "clamp(1rem, 4vw, 2.75rem)",
    "clusterGap": "clamp(0.6rem, 3.5vw, 1.75rem)",
    "contentMaxWidth": "min(70rem, 92vw)",
    "contentNarrow": "min(40rem, 94vw)",
    "cardPadding": "clamp(1rem, 2.75vw, 2rem)",
    "sectionHeaderGap": "clamp(0.75rem, 2.5vw, 1.5rem)",
    "touchTargetMin": "clamp(2.75rem, 2.4rem + 0.8vw, 3.25rem)"
  },
  "radii": {
    "$description": "Border radius scale for surfaces and components.",
    "xs": "6px",
    "sm": "10px",
    "md": "14px",
    "lg": "20px",
    "xl": "28px",
    "pill": "999px",
    "full": "9999px"
  },
  "shadow": {
    "$description": "Shadow tokens tuned for the ruby themed surfaces.",
    "xs": "0 1px 2px rgba(154, 17, 44, 0.18)",
    "sm": "0 4px 12px rgba(154, 17, 44, 0.24)",
    "md": "0 12px 24px rgba(200, 24, 58, 0.3)",
    "lg": "0 18px 40px rgba(200, 24, 58, 0.36)"
  },
  "motion": {
    "$description": "Motion durations, easings and accessibility aware queries.",
    "duration": {
      "instant": "80ms",
      "shortest": "120ms",
      "shorter": "160ms",
      "short": "220ms",
      "medium": "320ms",
      "long": "480ms"
    },
    "easing": {
      "standard": "cubic-bezier(0.2, 0, 0, 1)",
      "emphasized": "cubic-bezier(0.32, 0.94, 0.6, 1)",
      "entrance": "cubic-bezier(0.3, 0, 0.45, 1)",
      "exit": "cubic-bezier(0.35, 0, 0.65, 1)"
    },
    "mediaQueries": {
      "reduceMotion": "(prefers-reduced-motion: reduce)"
    }
  }
}
